{
  "namespace": "aivss",
  "key": "GM",
  "version": "1.0.0",
  "name": "Gradient Masking/Obfuscation",
  "description": "Measures the effectiveness of gradient masking or obfuscation techniques used to protect against gradient-based attacks.",
  "schemaVersion": "2.0.0",
  "values": [
    {
      "key": "H",
      "name": "Hidden",
      "description": "Gradients are completely hidden or formally proven to be unrecoverable."
    },
    {
      "key": "S",
      "name": "Strong",
      "description": "Strong gradient masking techniques used, making gradient-based attacks significantly more difficult."
    },
    {
      "key": "B",
      "name": "Basic",
      "description": "Basic gradient obfuscation methods employed, but gradients can still be partially recovered."
    },
    {
      "key": "N",
      "name": "None",
      "description": "Gradients are easily accessible and interpretable, no masking techniques used."
    }
  ]
}
